{"songs": [{"title": "Ladrillo", "album": null, "year": null, "lyrics": "En la penitenciaria\nLadrillo llora sus penas\nCumpliendo injusta condena\nAunque mato en buena ley\n\nLos jueces lo condenaron\nSin comprender que Ladrillo\nFue siempre bueno sencillo\nTrabjador como un buey\n\nLadrillo esta en la carcel el barrio lo estra\u00f1a\nSus dulces seratas ya no se oyen mas\nLos chicos ya no tiene su amigo querido\nQue siempre moneditas les dab al pasar\n\nLos Jueves y Domingo se ve una viejita\nLlevar un paquetito al que preso esta\nDe vuelta la viejita los ni\u00f1os preguntan\nLadrillo cuando sale, solo dios sabra\n\nEl dia que con un baile su compromiso cellaba\nUn compadron molestba a la que era su amor\nJugando entonces su vida, enduelo criollo Ladrillo\nLe sepulto su cuchillo, partiendole el corazon\n\nLadrillo esta en la carcel el barrio lo estra\u00f1a\nSus dulces seratas ya no se oyen mas\nLos chicos ya no tiene su amigo querido\nQue siempre moneditas les dab al pasar\n\nLos Jueves y Domingo se ve una viejita\nLlevar un paquetito al que preso esta\nDe vuelta la viejita los ni\u00f1os preguntan\nLadrillo cuando sale, solo dios sabra", "image": "https://images.genius.com/cee193612934a401bb7fda2e54ab24ad.1000x1000x1.jpg"}], "artist": "Carlos Gardel"}