{"songs": [{"title": "Hoy Desde Aqui", "album": null, "year": null, "lyrics": "(Pablo Neruda - Eduardo Galeano - \u00c1ngel Oliva - Juan Capagorry -\nMilton Schinca - Alfredo Zitarrosa)\n\nEl pueblo\n(Pablo Neruda)\n\nDe aquel hombre me acuerdo y no han pasado\nSino dos siglos desde que lo vi\nNo anduvo ni a caballo ni en carroza:\nA puro pie\nDeshizo\nLas distancias\nY no llevaba espada ni armadura\nSino redes al hombro\nHacha o martillo o pala\nNunca apale\u00f3 a ninguno de su especie:\nSu haza\u00f1a fue contra el agua o la tierra\nContra el trigo para que hubiera pan\nContra el \u00e1rbol gigante para que diera le\u00f1a\nContra los muros para abrir las puertas\nContra la arena construyendo muros\nY contra el mar para hacerlo parir\n\nLo conoc\u00ed y a\u00fan no se me borra\n\nCayeron en pedazos las carrozas\nLa guerra destruy\u00f3 puertas y muros\nLa ciudad fue un pu\u00f1ado de cenizas\nSe hicieron polvo todos los vestidos\nY \u00e9l para m\u00ed subsiste\nSobrevive en la arena\nCuando antes parec\u00eda\nTodo imborrable menos \u00e9l\n\nEn el ir y venir de las familias\nA veces fue mi padre o mi pariente\nO apenas si era \u00e9l o si no era\nTal vez aquel que no volvi\u00f3 a su casa\nPorque el agua o la tierra lo tragaron\nO lo mat\u00f3 una m\u00e1quina o un \u00e1rbol\nO fue aquel enlutado carpintero\nQue iba detr\u00e1s del ata\u00fad, sin l\u00e1grimas\nAlguien en fin que no ten\u00eda nombre\nQue se llamaba metal o madera\nY a quien miraron otros desde arriba\nSin ver la hormiga\nSino el hormiguero\nY que cuando sus pies no se mov\u00edan\nPorque el pobre cansado hab\u00eda muerto\nNo vieron nunca que no lo ve\u00edan:\nHab\u00eda ya otros pies en donde estuvo\n\nLos otros pies eran \u00e9l mismo\nTambi\u00e9n las otras manos\nEl hombre suced\u00eda:\nCuando ya parec\u00eda transcurrido\nEra el mismo de nuevo\nAll\u00ed estaba otra vez cavando tierra\nCortando tela, pero sin camisa\nAll\u00ed estaba y no estaba, como entonces\nSe hab\u00eda ido y estaba de nuevo\nY como nunca tuvo cementerio\nNi tumba, ni su nombre fue grabado\nSobre la piedra que cort\u00f3 sudando,*\nNunca sab\u00eda nadie que llegaba\nY nadie supo cuando se mor\u00eda\nAs\u00ed es que s\u00f3lo cuando el pobre pudo\nResucit\u00f3 otra vez sin ser notado\n\nEra el hombre sin duda, sin herencia\nSin vaca, sin bandera\nY no se distingu\u00eda entre los otros\nLos otros que eran \u00e9l\nDesde arriba era gris como el subsuelo\nComo el cuero era pardo\nEra amarillo cosechando trigo\nEra negro debajo de la mina\nEra color de piedra en el castillo\nEn el barco pesquero era color de at\u00fan\nY color de caballo en la pradera:\nC\u00f3mo pod\u00eda nadie distinguirlo\nSi era el inseparable, el elemento\nTierra, carb\u00f3n o mar vestido de hombre?\n\nDonde vivi\u00f3 crec\u00eda\nCuanto el hombre tocaba:\nLa piedra hostil\nQuebrada\nPor sus manos\nSe convert\u00eda en orden**\nY una a una formaron\nLa recta claridad del edificio\nHizo el pan con sus manos\nMoviliz\u00f3 los trenes\nSe poblaron de pueblos las distancias\nOtros hombres crecieron\nLlegaron las abejas\nY porque el hombre crea y multiplica\nLa primavera camin\u00f3 al mercado\nEntre panader\u00edas y palomas\n\nEl padre de los panes fue olvidado\n\u00e9l que cort\u00f3 y anduvo, machacando\nY abriendo surcos, acarreando arena\nCuando todo existi\u00f3 ya no exist\u00eda\n\u00e9l daba su existencia, eso era todo\nSali\u00f3 a otra parte a trabajar, y luego\nSe fue a morir rodando\nComo piedra del r\u00edo:\nAguas abajo lo llev\u00f3 la muerte\n\nYo, que lo conoc\u00ed, lo vi bajando\nHasta no ser sino lo que dejaba:\nCalles que apenas pudo conocer\nCasas que nunca y nunca habitar\u00eda\n\nY vuelvo a verlo, y cada d\u00eda espero\n\nLo veo en su ata\u00fad y resurrecto \n\nLo distingo entre todos\nLos que son sus iguales\nY me parece que no puede ser\nQue as\u00ed no vamos a ninguna parte\nQue suceder as\u00ed no tiene gloria\n\n* Alfredo Zitarrosa dice \"sobre la piedra que \u00e9l cort\u00f3 sudando\"\n** Alfredo Zitarrosa dice \"Donde vivi\u00f3 crec\u00eda. Cuando el hombre tocaba\n/ la piedra hostil / quebrada / por sus manos, / se convert\u00eda en\nOrden\"\n\nComentario\n(Eduardo Galeano)\n(por E. Galeano)\n\nAplicaron un plan de exterminio: arrasar la hierba, arrancar de ra\u00edz\nHasta la \u00faltima plantita todav\u00eda viva, regar la tierra con sal\nDespu\u00e9s, matar la memoria de la hierba. Estaba prohibido recordar. Se\nFormaban cuadrillas de presos. Por las noches los obligaban a tapar\nCon pintura blanca las frases de protesta que en otros tiempos cubr\u00edan\nLos muros de la ciudad. Pero la lluvia, de tanto golpear los muros\nIba disolviendo la pintura blanca y reaparec\u00edan, poquito a poco, las\nPorfiadas palabras\n\nApoya tu mano\n(\u00c1ngel Oliva)\n(por \u00c1. Oliva)\n\nApoya tu mano derecha en mi cabeza y con tu brazo izquierdo aprieta mi\nCintura. Pon tus labios en el umbral de mi boca, y acomp\u00e1\u00f1ame\nEs noche y all\u00ed est\u00e1n, sembrando, durmiendo debajo de los tornos\nApretados junto al horno fr\u00edo, compartiendo el tabaco y la foto del\nHijo\nPan y rosas para los hombres del mundo, para los que siembran el trigo\nY levantan la flor. No te vayas, conversa con ellos, y sabr\u00e1s qu\u00e9\nFuerza tienen las palabras con sudor, y ver\u00e1s m\u00fasculo a m\u00fasculo\nSostener gajo a gajo los gajos de la tierra\nAqu\u00ed est\u00e1n los obreros, ocupando y cantando, y volviendo a ocupar\nOcupando y cantando, cantando la luz en que se teje sangre reci\u00e9n\nCa\u00edda; sangre reci\u00e9n ca\u00edda y caliente porvenir. Pan y rosas para los\nHombres del mundo, para los amantes de la paz, para los iniciadores de\nLa m\u00e1quina y la producci\u00f3n maquinista, para los vestidores de los\nSitios por donde el hombre pasa, para los que siembran el trigo y\nLevantan la flor\nHoy cuando despert\u00e9, mir\u00e9 las paredes despintadas de mi cuarto y solt\u00e9\nUna carcajada, un beso y un pan. 15 de marzo de 1985. La luz resbala\nPor nuestros hombros, y los ojos se abren sin fierros ni fusiles;\nSomos nosotros, los del dolido traje gris y los versos clandestinos\nLos que sabemos seguro que entre espuelas, martillos y esperanza\nDulce y amarga, Patria, nos espera\n\nComentario\n(Eduardo Galeano)\n(por E. Galeano)\n\nAmigos de hace treinta a\u00f1os, de cuando yo estren\u00e9 los pantalones\nLargos en las manifestaciones callejeras, me estaban esperando en\nMontevideo. Hac\u00eda once a\u00f1os que no los ve\u00eda, casi doce, y desde\nEntonces hab\u00eda llovido mucha ceniza sobre el Uruguay. La tortura se\nHab\u00eda convertido en costumbre, la solidaridad en delito y la delaci\u00f3n\nEn virtud, la mentira y la desconfianza se hab\u00edan hecho necesidades\nCotidianas, y el miedo y el silencio, modos de vida. Pero no bien los\nVi, supe que esos viejos amigos hab\u00edan sabido guardar el fuego bajo la\nHelada, segu\u00edan siendo capaces de indignaci\u00f3n y de asombro y de\nChiquil\u00edn entusiasmo, y ahora ten\u00edan todas las edades a la vez\n\nY estamos\u2026\n(Juan Capagorry)\n(por J. Capagorry)\n\nY estamos\u2026 como saliendo de un pozo, desde una noche atroz\nInterminable, donde corr\u00edan desbocados caballos, pisoteaban sue\u00f1os\nRecuerdos y guitarras. Nos resultaba procaz, prohibido, amarlo desde\nAdentro, porque adentro ten\u00edamos la llaga punzante del dolor, dolor\nPor los tantos y tantos compa\u00f1eros, y en las manos se nos secaban las\nCaricias, lentas, y con llanto para las cabecitas de los ni\u00f1os. Y\nPens\u00e1bamos en otras manos, otras manos que pegaban, torturaban. Y\nAfuera la noche, atroz, interminable, y en ella, ellos buscando y\nBuscando compa\u00f1eros. Y bajo otros cielos, ojos de este cielo nuestro\nRevisando otros cielos, preguntando a otros cielos, y nosotros\nDeshaciendo todos nuestros recuerdos; y nosotros esperando cartas, que\nNo llegaban. Y afuera segu\u00eda la noche\u2026 atroz, interminable\n\nComentario\n(Eduardo Galeano)\n(por E. Galeano)\n\nRequiere m\u00e1s coraje la alegr\u00eda que la pena. A la pena, al fin y al\nCabo, estamos acostumbrados\n\nExhortaci\u00f3n a los j\u00f3venes\n(Milton Schinca)\n(por M. Schinca)\n\nMe dijeron que enrollaste la bandera del Frente, no como quien la\nGuarda hasta el pr\u00f3ximo acto, sino casi como quien est\u00e1 arriando una\nBandera. Est\u00e1s decepcionado porque el Frente no sac\u00f3 todos los votos\nQue t\u00fa hubieras querido. Un d\u00eda sentiste el orgullo de estar con el\nFrente, de ese Frente que pon\u00eda cada d\u00eda los presos, los desterrados y\nLos muertos, y en la calle y con el Frente viviste los grandes\nMomentos con que paso a paso se le fue ganando la pulseada al r\u00e9gimen\nHasta llegar por fin a su derrota final. Ahora pens\u00e1\u2026 en tu\nAdolescencia, en lo que caminaste por dentro de ti mismo, en lo que\nCamin\u00f3 el pa\u00eds junto contigo. \u00a1Cuidado!, porque est\u00e1s en un filo\nDif\u00edcil, en que la palabra decepci\u00f3n, con s\u00f3lo cambiarle un sonido, se\nTe puede convertir en deserci\u00f3n. Que no te ocurra eso. Enroll\u00e1 esa\nBandera pero despacito, pensando en todo lo que contiene, para vos\nMismo, para la gente que m\u00e1s te importa, para tu pa\u00eds. Ahora s\u00ed\nGuardala. Pero guardala como para sacarla en todos los momentos de los\nA\u00f1os que vienen, que el gesto de guardarla no se parezca, ni por\nAsomo, al gesto de quien estuviera arriando semejante bandera\n\nComentario\n(Eduardo Galeano)\n(por E. Galeano)\n\nLos muchachos se asoman a un pa\u00eds arrasado, donde encontrar trabajo\nResulta una haza\u00f1a, y sobrevivir un milagro; pero no asisten de brazos\nCruzados a la desgracia nacional. El sistema quiso castrar a los\nJ\u00f3venes uruguayos, y ellos son los m\u00e1s fecundos; quiso callarlos, y\nSon los m\u00e1s decidores; fracasaron quienes prohibieron el agua porque\nNo pudieron, porque nadie puede, prohibir la sed\n\nHoy te puedo decir\u2026\n(Alfredo Zitarrosa)\n(por Nancy Marino)\n\nHoy te puedo decir que no conf\u00edes\nEn el amor hambriento ni en la suerte\nSi estar vivo es viajar hacia la muerte\n\nLa vida es una viuda que sonr\u00ede\n\nCuando te toque hablar hazlo de modo\nQue el que escucha comprenda lo que sientes\nCuando debas obrar que sepan todos\nQue el fruto de tus obras es simiente\n\nNo te aconsejo el odio, pero escucha\nT\u00fa que en viaje de ida me recibes\n\nOdia profundamente a aquel que vive\nLuchando a muerte por odiar la dicha\n\nEl j\u00fabilo de ser un d\u00eda cualquiera\nParte del todo, en uno resumido\nEs el j\u00fabilo p\u00e1jaro del nido\nSaltando al \u00e1rbol de la primavera\n\nPero esas alas tuyas ya nacidas\nQuerr\u00e1n volar m\u00e1s lejos de este suelo:\nNunca olvides -volando- que la vida\nTe dio esas alas para alzar el vuelo\n\nEl pueblo (Continuaci\u00f3n)\n(Pablo Neruda)\n\nYo creo que en el trono debe estar\nEste hombre, bien calzado y coronado\n\nCreo que los que hicieron tantas cosas\nDeben ser due\u00f1os de todas las cosas\n\nY los que hacen el pan deben comer!\n\nY deben tener luz los de la mina!\n\nBasta ya de encadenados grises!\n\nBasta de p\u00e1lidos desaparecidos!\n\nNi un hombre m\u00e1s que pase sin que reine\n\nNi una sola mujer sin su diadema\n\nPara todas las manos guantes de oro\n\nFrutas del sol a todos los oscuros!*\n\nYo conoc\u00ed aquel hombre y cuando pude\nCuando ya tuve ojos en la cara\nCuando ya tuve la voz en la boca\nLo busqu\u00e9 entre las tumbas y le dije\nApret\u00e1ndole un brazo que a\u00fan no era polvo:\n\n\"Todos se ir\u00e1n, t\u00fa quedar\u00e1s viviente\n\nT\u00fa encendiste la vida\n\nT\u00fa hiciste lo que es tuyo.\"\n\nPor eso nadie se moleste cuando\nParece que estoy solo y no estoy solo,**\nNo estoy con nadie y hablo para todos:\n\nAlguien me est\u00e1 escuchando y no lo saben\nPero aquellos que canto y que lo saben\nSiguen naciendo y llenar\u00e1n el mundo\n\n* Alfredo Zitarrosa dice \"Frutas de sol a todos los oscuros!\"\n** Alfredo Zitarrosa dice \"parece que estoy solo y no estoy\"", "image": "https://images.genius.com/cfb79bdfe663abc4725e52a503c04d12.343x343x1.jpg"}], "artist": "Alfredo Zitarrosa"}