{"songs": [{"title": "Defensa Del Gaucho", "album": null, "year": null, "lyrics": "(Milonga A Mart\u00edn Fierro o Rom\u00e1n Gim\u00e9nez)\nEn este trovar sencillo\nLo que es gaucho te dir\u00e9\nBorrando la mala fe\nDel que lo volvi\u00f3 un cuchillo\nUn harag\u00e1n, s\u00f3lo un pillo\nBueno para el alancear\nO bueyes desjarretar\nEn las furiosas corambres\nCon los hijos muertos de hambre\nY \u00e9l guitarrita y trovar\nY el pobre en su condici\u00f3n\nDe servicial y parejo\nSin sospechar el manejo\nDel mandam\u00e1s o el patr\u00f3n\nPrimereaba en la funci\u00f3n\nDe las revueltas civiles\nAchur\u00e1ndose de a miles\nVecinos vueltos contrarios\nCon el polvo por sudario\nCon una cruz de fusiles\nY creyendo, as\u00ed, servir\nLa patria, sus claros trillos\nFue un oficio el del cuchillo\nY una raz\u00f3n: la de herir;\nNo supo nunca mentir\nFue por amistad y arrojo\nUn empecinado abrojo\nDe la loca caballada\nCon la muerte y la Patriada\nComo una venda en los ojos\nY despu\u00e9s, cuando volvi\u00f3\nTreinta a\u00f1os tengo de ausencia\nY, entre el yuyal, la querencia\nCasi no reconoci\u00f3\nNi siquiera desmont\u00f3\nClav\u00f3 la lanza en el suelo\nY semidesnudo, en pelo\nGalop\u00f3 hacia la tormenta\nEl que su dolor no sienta\nNo naci\u00f3 bajo este cielo\nAlguno fue a preguntar\nAl Juez de Paz o al cacique\nLos encontr\u00f3 de palique\nCon suertes para firmar\nY comenz\u00f3 a desconfiar\nQue en aquel reparto, nada\nNi una m\u00edsera tajada\nIba a quedar a su nombre\nPorque \u00e9l no era un prohombre\nCon apellido y espada\nY pele\u00f3 y se emborrach\u00f3\nComo el gaucho Mart\u00edn Fierro\nVuelto le\u00f3n top\u00f3 a los perros\nSin querer los matrere\u00f3\nY en alg\u00fan abra dej\u00f3\nSu perseguida pisada\nFue leyenda condenada\nCuento de espanto y de robo\nY el que lo empuj\u00f3 a ser lobo\nCom\u00eda la borregada\nQuiero que me entiendas bien\n\u00e9sta es la historia sencilla\nDel gaucho, de su Mansilla\nPor tanta gente de bien\nY, si me entendiste, ven\nSin l\u00e1grima, sin lamento\nTe pido el recogimiento\nDe un instante, para o\u00edrlo\nEn ese canto de mirlo\nEn esa lecci\u00f3n del viento\n(Los textos en cursiva corresponden a partes recitadas)", "image": "https://images.genius.com/cfb79bdfe663abc4725e52a503c04d12.343x343x1.jpg"}], "artist": "Alfredo Zitarrosa"}